holidays/__init__.py
holidays/constants.py
holidays/helpers.py
holidays/holiday_base.py
holidays/observed_holiday_base.py
holidays/py.typed
holidays/registry.py
holidays/utils.py
holidays/calendars/__init__.py
holidays/calendars/buddhist.py
holidays/calendars/chinese.py
holidays/calendars/custom.py
holidays/calendars/gregorian.py
holidays/calendars/hebrew.py
holidays/calendars/hindu.py
holidays/calendars/islamic.py
holidays/calendars/julian.py
holidays/calendars/julian_revised.py
holidays/calendars/persian.py
holidays/calendars/thai.py
holidays/countries/__init__.py
holidays/countries/albania.py
holidays/countries/algeria.py
holidays/countries/american_samoa.py
holidays/countries/andorra.py
holidays/countries/angola.py
holidays/countries/argentina.py
holidays/countries/armenia.py
holidays/countries/aruba.py
holidays/countries/australia.py
holidays/countries/austria.py
holidays/countries/azerbaijan.py
holidays/countries/bahrain.py
holidays/countries/bangladesh.py
holidays/countries/barbados.py
holidays/countries/belarus.py
holidays/countries/belgium.py
holidays/countries/belize.py
holidays/countries/bolivia.py
holidays/countries/bosnia_and_herzegovina.py
holidays/countries/botswana.py
holidays/countries/brazil.py
holidays/countries/brunei.py
holidays/countries/bulgaria.py
holidays/countries/burkina_faso.py
holidays/countries/burundi.py
holidays/countries/cambodia.py
holidays/countries/cameroon.py
holidays/countries/canada.py
holidays/countries/chad.py
holidays/countries/chile.py
holidays/countries/china.py
holidays/countries/colombia.py
holidays/countries/costa_rica.py
holidays/countries/croatia.py
holidays/countries/cuba.py
holidays/countries/curacao.py
holidays/countries/cyprus.py
holidays/countries/czechia.py
holidays/countries/denmark.py
holidays/countries/djibouti.py
holidays/countries/dominican_republic.py
holidays/countries/ecuador.py
holidays/countries/egypt.py
holidays/countries/el_salvador.py
holidays/countries/estonia.py
holidays/countries/eswatini.py
holidays-0.33.dist-info/LICENSE
holidays-0.33.dist-info/METADATA
holidays-0.33.dist-info/WHEEL
holidays-0.33.dist-info/top_level.txt
holidays-0.33.dist-info/RECORD
