Metadata-Version: 2.1
Name: holidays
Version: 0.33
Summary: Generate and work with holidays in Python
Home-page: https://github.com/vacanza/python-holidays
Author: Maurizio Montel (dr-prodigy)
Author-email: dr.prodigy.github@gmail.com
Maintainer: Arkadii Yakovets (arkid15r)
Maintainer-email: ark@cho.red
License: MIT
Platform: any
Classifier: Development Status :: 4 - Beta
Classifier: Intended Audience :: Developers
Classifier: License :: OSI Approved :: MIT License
Classifier: Operating System :: OS Independent
Classifier: Programming Language :: Python
Classifier: Programming Language :: Python :: 3
Classifier: Programming Language :: Python :: 3 :: Only
Classifier: Programming Language :: Python :: Implementation :: CPython
Classifier: Programming Language :: Python :: Implementation :: PyPy
Classifier: Topic :: Office/Business :: Scheduling
Classifier: Topic :: Software Development :: Libraries :: Python Modules
Classifier: Topic :: Software Development :: Localization
Requires-Python: >=3.8
License-File: LICENSE
Requires-Dist: python-dateutil
